model_test_scripts/__init__.py
model_test_scripts/script_convert_model.py
test/query/__init__.py
test/query/property_constraint.py
test/query/vital_graph_query.py
test/query/vital_query.py
test/query/vital_select_query.py
test_scripts/__init__.py
test_scripts/create_gm_test.py
test_scripts/create_node_test.py
test_scripts/create_property_test.py
test_scripts/script_convert_model.py
test_scripts/script_embedding_model.py
test_scripts/script_fuseki.py
test_scripts/script_graph_collection.py
test_scripts/script_hnswlib.py
test_scripts/script_memory_service.py
test_scripts/script_metaql_builder_query_impl.py
test_scripts/script_metaql_graph_builder.py
test_scripts/script_metaql_select_builder.py
test_scripts/script_metaql_vector_builder.py
test_scripts/script_neptune_query.py
test_scripts/script_onnx.py
test_scripts/script_package_discovery.py
test_scripts/script_query_builder.py
test_scripts/script_vector_separation.py
test_scripts/script_virtuoso_odbc_connection.py
test_scripts/script_vital_service.py
test_scripts/script_vs.py
test_scripts/script_weaviate.py
test_scripts/graphobject/__init__.py
test_scripts/graphobject/test_dict_basic.py
test_scripts/graphobject/test_equality_basic.py
test_scripts/graphobject/test_json_basic.py
test_scripts/graphobject/test_jsonld_basic.py
test_scripts/graphobject/test_property_uri_mapping.py
test_scripts/graphobject/test_rdf_basic.py
test_scripts/graphobject/test_triples_basic.py
test_scripts/jsonld/__init__.py
test_scripts/jsonld/test_class_inheritance_debug.py
test_scripts/jsonld/test_jsonld_context_generation.py
test_scripts/jsonld/test_jsonld_identifier_consistency.py
test_scripts/jsonld/test_jsonld_list_operations.py
test_scripts/jsonld/test_jsonld_serialization.py
test_scripts/jsonld/test_jsonld_single_object.py
test_scripts/jsonld/test_jsonld_validation.py
test_scripts/jsonld/test_multivalue_bug_reproduction.py
test_scripts/jsonld/test_multivalue_properties.py
test_scripts/jsonld/test_multivalue_simple.py
vital_ai_vitalsigns-0.1.46.dist-info/licenses/LICENSE
vital_ai_vitalsigns-0.1.46.dist-info/METADATA
vital_ai_vitalsigns-0.1.46.dist-info/WHEEL
vital_ai_vitalsigns-0.1.46.dist-info/entry_points.txt
vital_ai_vitalsigns-0.1.46.dist-info/top_level.txt
vital_ai_vitalsigns-0.1.46.dist-info/RECORD
