Metadata-Version: 2.4
Name: vital-ai-vitalsigns
Version: 0.1.46
Summary: VitalSigns knowledge graph bindings
Home-page: https://github.com/vital-ai/vital-vitalsigns-python
Author: Marc Hadfield
Author-email: marc@vital.ai
License: Apache License 2.0
Classifier: Programming Language :: Python :: 3.12
Classifier: License :: OSI Approved :: Apache Software License
Classifier: Operating System :: OS Independent
Requires-Python: >=3.12
License-File: LICENSE
Requires-Dist: packaging>=23.0
Requires-Dist: python-dotenv>=1.0.1
Requires-Dist: rdflib>=7.0.0
Requires-Dist: PyYAML>=6.0.1
Requires-Dist: PyLD>=2.0.0
Requires-Dist: numpy>=1.26.4
Requires-Dist: hnswlib>=0.8.0
Requires-Dist: owlready2==0.46
Requires-Dist: owlrl==6.0.2
Requires-Dist: qdrant-client
Requires-Dist: SPARQLWrapper==2.0.0
Requires-Dist: pyshacl==0.25.0
Requires-Dist: requests>=2.31.0
Requires-Dist: PyODBC>=5.1.0
Requires-Dist: onnxruntime>=1.18.0
Requires-Dist: onnx>=1.16.1
Requires-Dist: tzdata>=2024.1
Requires-Dist: pytz>=2024.1
Requires-Dist: python-dateutil>=2.9.0
Requires-Dist: transformers>=4.49.0
Requires-Dist: vital-model-paraphrase-MiniLM-onnx>=0.2.1
Requires-Dist: psutil>=6.0.0
Requires-Dist: urllib3
Requires-Dist: paramiko==3.5.0
Requires-Dist: scp==0.15.0
Requires-Dist: datasketch>=1.6.5
Provides-Extra: base
Requires-Dist: onnxruntime; extra == "base"
Requires-Dist: numpy; extra == "base"
Provides-Extra: dev
Requires-Dist: nltk; extra == "dev"
Requires-Dist: matplotlib; extra == "dev"
Requires-Dist: networkx; extra == "dev"
Requires-Dist: torch>=2.3.0; extra == "dev"
Requires-Dist: sentence_transformers==3.3.1; extra == "dev"
Requires-Dist: transformers; extra == "dev"
Requires-Dist: wheel>=0.43.0; extra == "dev"
Requires-Dist: dill; extra == "dev"
Requires-Dist: pytest; extra == "dev"
Requires-Dist: scikit-learn>=1.6.1; extra == "dev"
Requires-Dist: scipy>=1.15.2; extra == "dev"
Dynamic: author
Dynamic: author-email
Dynamic: classifier
Dynamic: description
Dynamic: description-content-type
Dynamic: home-page
Dynamic: license
Dynamic: license-file
Dynamic: provides-extra
Dynamic: requires-dist
Dynamic: requires-python
Dynamic: summary
